bipwrapper/__init__.py
bipwrapper/api.py
bipwrapper/config.py
bipwrapper/environment.py
bipwrapper/type.py
bipwrapper/model/__init__.py
bipwrapper/model/document.py
bipwrapper/model/location.py
bipwrapper/model/poll.py
bipwrapper/model/postback.py
bipwrapper/model/request.py
bipwrapper/model/vcard.py
bipwrapper/service/__init__.py
bipwrapper/service/base.py
bipwrapper/service/group.py
bipwrapper/service/multi.py
bipwrapper/service/single.py
bipwrapper/service/upload.py
bipwrapper/type/__init__.py
bipwrapper/type/address_type.py
bipwrapper/type/button_type.py
bipwrapper/type/content_type.py
bipwrapper/type/ctype.py
bipwrapper/type/media_type.py
bipwrapper/type/poll_type.py
bipwrapper-1.3.4.dist-info/LICENSE
bipwrapper-1.3.4.dist-info/METADATA
bipwrapper-1.3.4.dist-info/WHEEL
bipwrapper-1.3.4.dist-info/top_level.txt
bipwrapper-1.3.4.dist-info/RECORD
