Metadata-Version: 2.1
Name: bipwrapper
Version: 1.3.4
Summary: BIP Messenger API Wrapper
Home-page: https://github.com/semudu/bipwrapper
Author: Serhat Durmaz
Author-email: serhat.md@gmail.com
License: MIT
Download-URL: https://github.com/semudu/bipwrapper/archive/v1.3.4.tar.gz
Keywords: BIP,WRAPPER,BIPMESSENGER,BIPWRAPPER
Platform: UNKNOWN
Classifier: Development Status :: 5 - Production/Stable
Classifier: Intended Audience :: Developers
Classifier: Topic :: Software Development :: Build Tools
Classifier: License :: OSI Approved :: MIT License
Classifier: Programming Language :: Python :: 3
Classifier: Operating System :: OS Independent
Requires-Dist: requests
